awesome_actus_lib/__init__.py
awesome_actus_lib/analysis/Analysis.py
awesome_actus_lib/analysis/__init__.py
awesome_actus_lib/analysis/income.py
awesome_actus_lib/analysis/liquidity.py
awesome_actus_lib/analysis/value.py
awesome_actus_lib/controller/Infrastructure.py
awesome_actus_lib/controller/__init__.py
awesome_actus_lib/models/ANN_gen.py
awesome_actus_lib/models/BCS_gen.py
awesome_actus_lib/models/CAPFL_gen.py
awesome_actus_lib/models/CEC_gen.py
awesome_actus_lib/models/CEG_gen.py
awesome_actus_lib/models/CLM_gen.py
awesome_actus_lib/models/COM_gen.py
awesome_actus_lib/models/CSH_gen.py
awesome_actus_lib/models/FUTUR_gen.py
awesome_actus_lib/models/FXOUT_gen.py
awesome_actus_lib/models/LAM_gen.py
awesome_actus_lib/models/LAX_gen.py
awesome_actus_lib/models/NAM_gen.py
awesome_actus_lib/models/OPTNS_gen.py
awesome_actus_lib/models/PAM_gen.py
awesome_actus_lib/models/RiskFactor.py
awesome_actus_lib/models/STK_gen.py
awesome_actus_lib/models/SWAPS_gen.py
awesome_actus_lib/models/SWPPV_gen.py
awesome_actus_lib/models/UMP_gen.py
awesome_actus_lib/models/__init__.py
awesome_actus_lib/models/cashFlowStream.py
awesome_actus_lib/models/contractModel.py
awesome_actus_lib/models/contractPlot.py
awesome_actus_lib/models/contract_terms_generated.py
awesome_actus_lib/models/portfolio.py
awesome_actus_lib/models/portfolioPlot.py
awesome_actus_lib/utils/__init__.py
awesome_actus_lib/utils/actus_applicability_rules_grouped.py
awesome_actus_lib/utils/businessRuleValidator.py
awesome_actus_lib/utils/contract_type_map.py
awesome_actus_lib/utils/utils.py
awesome_actus_lib-1.0.11.dist-info/licenses/LICENSE
awesome_actus_lib-1.0.11.dist-info/METADATA
awesome_actus_lib-1.0.11.dist-info/WHEEL
awesome_actus_lib-1.0.11.dist-info/top_level.txt
awesome_actus_lib-1.0.11.dist-info/RECORD
