Metadata-Version: 2.4
Name: awesome_actus_lib
Version: 1.0.11
Summary: Modular Python Package for Financial Contract Modelling with the ACTUS Standard
Author-email: maierdon <whyaxis21@gmail.com>
License: MIT License
Project-URL: Homepage, https://github.com/maierdon/awesome_actus_lib
Project-URL: Documentation, https://awesomeactuslibrarydoc.vercel.app
Project-URL: Issues, https://github.com/maierdon/awesome_actus_lib/issues
Classifier: Development Status :: 5 - Production/Stable
Classifier: Intended Audience :: Developers
Classifier: Intended Audience :: Financial and Insurance Industry
Classifier: License :: OSI Approved :: MIT License
Classifier: Programming Language :: Python :: 3
Classifier: Operating System :: OS Independent
Requires-Python: >=3.8
License-File: LICENSE
Requires-Dist: matplotlib>=3.5.2
Requires-Dist: numpy>=1.24.2
Requires-Dist: pandas>=1.4.2
Requires-Dist: python-dateutil>=2.9.0.post0
Requires-Dist: requests>=2.32.4
Dynamic: license-file
